[{"model": "web.greeting", "pk": 1, "fields": {"when": "2020-09-06T19:44:50.994Z"}}, {"model": "web.greeting", "pk": 2, "fields": {"when": "2020-09-06T19:45:57.083Z"}}, {"model": "web.greeting", "pk": 3, "fields": {"when": "2020-09-11T17:08:41.127Z"}}, {"model": "web.greeting", "pk": 4, "fields": {"when": "2020-09-11T17:25:11.375Z"}}, {"model": "web.greeting", "pk": 5, "fields": {"when": "2020-09-12T15:44:51.250Z"}}, {"model": "web.greeting", "pk": 6, "fields": {"when": "2020-09-12T15:44:51.460Z"}}, {"model": "web.url", "pk": 1, "fields": {"title": "Подставка для ножа", "url": "https://www.youtube.com/embed/YWgFCe5tUso", "file_id": "None"}}, {"model": "web.url", "pk": 2, "fields": {"title": "Ореховая пешка", "url": "https://www.youtube.com/embed/dRTze2IpB-Y", "file_id": "None"}}, {"model": "web.url", "pk": 3, "fields": {"title": "Тестирование инструмента", "url": "https://youtube.com/embed/XsF2A3_oZVc", "file_id": "None"}}, {"model": "web.url", "pk": 4, "fields": {"title": "Ложки - близняшки", "url": "https://youtube.com/embed/Zwfz6uKAQbU", "file_id": "None"}}, {"model": "web.url", "pk": 5, "fields": {"title": "Педаль акселератора", "url": "https://youtube.com/embed/nUTvuZ7WaMY", "file_id": "None"}}, {"model": "web.url", "pk": 6, "fields": {"title": "Шахматы", "url": "https://youtube.com/embed/0qrO8RlsuGw", "file_id": "None"}}, {"model": "web.url", "pk": 7, "fields": {"title": "Огромная скалка", "url": "https://youtube.com/embed/Qh5uQvJU-7c", "file_id": "None"}}, {"model": "web.url", "pk": 8, "fields": {"title": "Эталон", "url": "https://youtube.com/embed/luaINct2WDA", "file_id": "None"}}]